tcai_pay_x/__init__.py
tcai_pay_x/__main__.py
tcai_pay_x/webapp.py
tcai_pay_x/templates/index.html
tcai_pay_x/templates/preview.html
tcai_pay_x/utils/__init__.py
tcai_pay_x/utils/ocr_utils.py
tcai_pay_x-0.1.0.dist-info/METADATA
tcai_pay_x-0.1.0.dist-info/WHEEL
tcai_pay_x-0.1.0.dist-info/entry_points.txt
tcai_pay_x-0.1.0.dist-info/top_level.txt
tcai_pay_x-0.1.0.dist-info/RECORD
