Metadata-Version: 2.4
Name: tcai-pay-x
Version: 0.1.0
Summary: A Flask-based web app for matching invoices to purchase orders using OCR and fuzzy matching.
Author: The Celeritas AI
Author-email: business@theceleritasai.com
Classifier: Programming Language :: Python :: 3
Classifier: Framework :: Flask
Classifier: License :: OSI Approved :: MIT License
Classifier: Operating System :: OS Independent
Requires-Python: >=3.8
Requires-Dist: Flask==3.1.1
Requires-Dist: numpy==2.2.6
Requires-Dist: pandas==2.2.3
Requires-Dist: openpyxl==3.1.5
Requires-Dist: pytesseract==0.3.13
Requires-Dist: pdf2image==1.17.0
Requires-Dist: pillow==11.2.1
Requires-Dist: RapidFuzz==3.13.0
Requires-Dist: python-dateutil==2.9.0.post0
Requires-Dist: packaging==25.0
Dynamic: author
Dynamic: author-email
Dynamic: classifier
Dynamic: description
Dynamic: description-content-type
Dynamic: requires-dist
Dynamic: requires-python
Dynamic: summary
